{"id": "CSC299Y5Y20199", "code": "CSC299Y5Y", "name": "Research Opportunity Program", "description": "This courses provides a richly rewarding opportunity for students in their second year to work in the research project of a professor in return for 299Y course credit. Students enrolled have an opportunity to become involved in original research, learn research methods and share in the excitement and discovery of acquiring new knowledge. Participating faculty members post their project descriptions for the following summer and fall/winter sessions in early February and students are invited to apply in early March. See\u00ffExperiential and International Opportunities\u00fffor more details.", "division": "University of Toronto Mississauga", "department": "Mathematical and Computational Sciences", "prerequisites": "", "exclusions": "", "level": 200, "campus": "UTM", "term": "2019 Fall", "breadths": [], "meeting_sections": [{"code": "L0101", "instructors": [], "times": [], "size": 5, "enrolment": 0}]}