{"name": "South Asian Civilizations", "degrees": ["HBA"], "notes": [], "programs": [{"name": "South Asian Civilizations (Arts)", "level": "Minor", "code": "ERMIN1333", "type": "Type 1", "notes": [], "courses": {"year1": ["ANT102H5", "HIS101H5", "POL114H5", "RLG101H5", "SOC100H5", "VST100H5"], "year2": ["ARA211Y5", "ARA212Y5", "CIN215H5", "DTS201H5", "FAH281H5", "FAH282H5", "HIN212Y5", "HIS211H5", "HIS212H5", "HIS282H5", "PRS210Y5", "RLG204H5", "RLG205H5", "RLG206H5", "RLG207H5", "RLG208H5", "SAN291Y5", "URD212Y5"], "year3": ["ANT310H5", "ANT316H5", "ANT320H5", "ARA312Y5", "CIN302H5", "FAH385H5", "FAH395H5", "GGR367H5", "HIN311H5", "HIN312Y5", "HIS366H5", "HIS382H5", "HIS386H5", "HIS394H5", "POL303Y5", "POL304Y5", "PRS310Y5", "RLG304H5", "RLG305H5", "RLG307H5", "RLG308H5", "RLG310H5", "RLG347H5", "RLG348H5", "RLG356H5", "RLG360H5", "RLG370H5", "RLG371H5", "RLG373H5", "RLG374H5", "SAN392Y5", "SOC354H5", "SOC375H5", "URD312Y5", "VCC306H5", "VCC360H5", "WGS335H5", "WGS368H5"], "year4": ["ARA412Y5", "FAH465H5", "FAH495H5", "HIN411H5", "HIN412Y5", "HIS484H5", "HIS493H5", "POL446H5", "RLG449H5", "RLG450H5", "RLG451Y5", "RLG452H5", "RLG460H5", "RLG470H5", "VCC406H5"]}}]}