{"name": "Theatre, Drama and Performance Studies", "degrees": ["HBA"], "notes": ["Additional DRE courses and the following drama-related courses can be used to fulfill the requirements for any Theatre, Drama and Performance Studies program:CIN202H5, 301H5*; 302H5*; 303H5*; CLA300H5; ENG220Y5, 330H5, 331H5*, 335H5*, 336H5*, 337H5, 340H5*, 341H5*, 342H5*, 352H5*, 424H5*/425H5*/ 426H5* (when drama related), 434H5*/435H5*/436H5* (when drama related), 460H5*/461H*/462H5*/463H5* (when drama related); 470H5*/471H5*/472H5*/473H5* (when drama related), FAH475H5, FRE317H5, 393H5, 397H5; GER353H5, 355H5*; ITA242H5, 243H5, 246H5, 247H5, 307H5, 315Y5, 342H5, 343H5, 413Y5, 490Y5, 495Y5.*= Departmental prerequisites", "Students enrolled in Specialist and Major programs in Drama who have completed 2.0 DRE credits may enrol in ENG330H5, 331H5, 335H5, 336H5, 340H5, 341H5, 342H5"], "programs": [{"name": "Theatre and Drama Studies (Arts)", "level": "Specialist", "code": "ERSPE1880", "type": "Type 3", "notes": [], "courses": {"year1": ["DRS121H5", "ENG121H5"], "year2": ["DRE200H5", "DRS221H5"], "year3": ["DRS321H5"], "year4": ["DRS421H5"]}}, {"name": "Theatre, Drama and Performance Studies (Arts)", "level": "Major", "code": "ERMAJ2468", "type": "Type 1", "notes": [], "courses": {"year1": ["ENG121H5"], "year2": ["DRE200H5"], "year3": [], "year4": []}}, {"name": "Theatre, Drama and Performance Studies (Arts)", "level": "Minor", "code": "ERMIN2468", "type": "Type 1", "notes": [], "courses": {"year1": ["ENG121H5"], "year2": ["CIN202H5", "DRE200H5", "ENG220Y5", "ITA242H5"], "year3": ["CLA300H5", "ENG330H5", "FRE317H5", "GER353H5"], "year4": ["FAH475H5"]}}]}